[1,["ecpdLyjvZBwrvm+cedCcQy","95c1VlCvNDUK47MmHaOkCu","a9h9ExJAJBb6LinGvcLR0m","4f3Pr7witMsK09kryLjFVU","7a/QZLET9IDreTiBfRn2PD","f0BIwQ8D5Ml7nTNQbh1YlS","e97GVMl6JHh5Ml5qEDdSGa","29FYIk+N1GYaeWH/q1NxQO","a2MjXRFdtLlYQ5ouAFv/+R","33QZ10JCNGvIQOf4OfGWQj","9fECZQlmJER4b8xAcjs7yy","dbeUHharlLo6zCra1n//SQ","7avUk6vJlIJaqR5HCoHdrc","c4goZNCjdKUIRrgXMs9lQl","71VhFCTINJM6/Ky3oX9nBT","0btR3cPIZE9IZSOUcNi7ZX","50TTrxb3ZFhrklUxHBLrRw","45U1rMQSVBlJ13D9dOm1i9","9cKap1KQlE77ZQrWRdF8Hx","08JS1knqZBw6MPGe/cDiGF","2djKfpffJH3oy9d9dCULMG","b3dswrDKpIfJWXbJoi2PqN","02delMVqdBD70a/HSD99FK","e0G2g5gdFMjbeavxrbF4lW","faPUUS/q9ARqVuIQX0L5Gl","0fQDe9OQlP36p5iBbv9FnT","0eI/WOpj9Op67j6drDP/XD","76zh4XvlhJQbRAJxStSO4u","6cMJCUyKdCAZscxo03Bues","01gL595xxIDI1bK+kkuTbW","de4fojS5tMpr0UqEsuE/YP","79zqkZSO9Pcquim/o9g5BP","e2SQR63Q5CkrW3A85NpsP2","3dNRiPkZBAWJngLw+TXlGa","acLmbEj35C8rY6pRny4C5m","a08HPWEFNNuYkSZzqB/L9Y","14m/yVEk1F666vbSuLng48","b5R7XwstVDZYd3t4wXwb9h","5fNNChVgBEb6pi9gO2TyXV","91ziwDsYFCAK51K/Lzoni9","1ahpNglqhEMZiEWEsYhmN+","1eIy0gc1JBdbEK9cdWeyOx","0fV2KOjQNDCa2mA5bousep","cbA567UidHvIuesz0j3t2e","03FNMiAjhAsp9v1KTmFy4E","9dIpqJij9HN5sBXAdx2QLG","17i/3ipTJL2J3qjGeKA7dq","b4P/PCArtIdIH38t6mlw8Y","e8Ueib+qJEhL6mXAHdnwbi"],["node","_spriteFrame","_textureSetter","_N$skeletonData","_parent","_N$normalSprite","_N$pressedSprite","_N$hoverSprite","_N$disabledSprite","spriteFrame","Prizes_Infor","cannnottouch","AlretNode","ChanceText","Prize","wheel_out_Light","Nail","TopLight","Title","wheel_out","wheel","_N$target","scene","_N$file"],["cc.SpriteFrame",["cc.Node",["_name","_active","_opacity","_objFlags","_id","_components","_contentSize","_parent","_trs","_children","_color","_eulerAngles","_anchorPoint"],-2,9,5,1,7,2,5,5,5],["cc.Label",["_string","_fontSize","_N$overflow","_lineHeight","_N$verticalAlign","_N$horizontalAlign","_styleFlags","_isSystemFontUsed","_enableWrapText","_N$cacheMode","node","_materials"],-7,1,3],["cc.Sprite",["_sizeMode","_type","node","_materials","_spriteFrame"],1,1,3,6],["sp.Skeleton",["defaultSkin","_preCacheMode","_animationName","defaultAnimation","loop","_playTimes","node","_materials","_N$skeletonData"],-3,1,3,6],["cc.Button",["_N$transition","node","clickEvents","_N$normalColor","_N$pressedColor","_N$disabledColor","_N$target","_N$normalSprite","_N$pressedSprite","_N$hoverSprite","_N$disabledSprite"],2,1,9,5,5,5,1,6,6,6,6],["cc.ClickEvent",["_componentId","handler","customEventData","target"],0,1],["cc.Widget",["_alignFlags","alignMode","_originalWidth","_originalHeight","node"],-1,1],["cc.LabelAtlas",["_name","fontSize","_fntConfig"],0],["cc.SceneAsset",["_name","asyncLoadAssets"],1],["cc.Node",["_name","_parent","_components","_contentSize","_trs"],2,1,2,5,7],["cc.Canvas",["_fitWidth","node","_designResolution"],2,1,5],["231fb6ZVWNN944v7V0dlDwZ",["node","wheel","wheel_out","Title","TopLight","Nail","wheel_out_Light","Prize","ChanceText","AlretNode","cannnottouch","Prizes_Infor"],3,1,1,1,1,1,1,1,1,1,1,1,1],["47ce2xxDsBPgqV10snO3sxM",["node"],3,1],["cc.BlockInputEvents",["node"],3,1],["cc.LabelOutline",["_width","node","_color"],2,1,5],["cc.Mask",["_type","_N$alphaThreshold","node","_materials"],1,1,3],["cc.Scene",["_name","_children","_anchorPoint","_trs"],2,2,5,7],["cc.Camera",["_clearFlags","_depth","node"],1,1]],[[3,2,3,4,1],[1,0,7,9,5,6,8,2],[3,0,2,3,4,2],[1,0,7,5,6,8,2],[1,0,7,5,6,2],[1,0,7,9,5,6,2],[2,0,1,3,6,5,4,2,10,11,8],[15,0,1,2,2],[16,0,1,2,3,3],[1,0,7,9,5,10,6,8,11,2],[1,0,2,7,5,6,8,11,3],[4,0,3,1,2,6,7,8,5],[5,0,1,2,3,4,5,6,7,8,9,10,2],[6,0,1,3,3],[8,0,1,2,4],[9,0,1,3],[1,0,4,9,5,6,8,3],[1,0,9,8,2],[1,0,1,2,7,9,5,10,6,8,4],[1,0,9,5,6,8,2],[1,0,7,9,8,2],[1,0,3,9,5,6,8,3],[1,0,1,7,9,5,6,3],[1,0,7,5,10,6,8,2],[1,0,1,7,9,5,6,12,8,3],[1,0,1,2,7,5,6,4],[1,0,7,5,2],[1,0,1,7,5,6,8,11,3],[1,0,3,7,5,10,6,3],[10,0,1,2,3,4,2],[11,0,1,2,2],[7,0,4,2],[7,1,0,2,3,4,5],[12,0,1,2,3,4,5,6,7,8,9,10,11,1],[13,0,1],[3,1,0,2,3,4,3],[3,2,3,1],[14,0,1],[2,0,1,3,2,10,11,5],[2,0,1,3,7,5,4,2,10,11,8],[2,0,1,3,6,4,2,10,11,7],[2,0,1,8,5,4,2,9,10,11,8],[4,0,1,2,6,7,8,4],[4,0,1,6,7,8,3],[4,0,3,1,4,2,5,6,7,8,7],[5,0,1,2,2],[5,1,2,1],[6,0,1,2,4],[6,0,1,2,3,4],[17,0,1,2,3,2],[18,0,1,2,3]],[[[[14,"金色字",206.8,{"commonHeight":235,"fontSize":206,"atlasName":"金色數字01","fontDefDictionary":{"48":{"xOffset":0,"yOffset":0,"xAdvance":140,"rect":{"x":0,"y":0,"width":140,"height":235}},"49":{"xOffset":0,"yOffset":0,"xAdvance":140,"rect":{"x":140,"y":0,"width":140,"height":235}},"50":{"xOffset":0,"yOffset":0,"xAdvance":140,"rect":{"x":280,"y":0,"width":140,"height":235}},"51":{"xOffset":0,"yOffset":0,"xAdvance":140,"rect":{"x":420,"y":0,"width":140,"height":235}},"52":{"xOffset":0,"yOffset":0,"xAdvance":140,"rect":{"x":560,"y":0,"width":140,"height":235}},"53":{"xOffset":0,"yOffset":0,"xAdvance":140,"rect":{"x":700,"y":0,"width":140,"height":235}},"54":{"xOffset":0,"yOffset":0,"xAdvance":140,"rect":{"x":840,"y":0,"width":140,"height":235}},"55":{"xOffset":0,"yOffset":0,"xAdvance":140,"rect":{"x":980,"y":0,"width":140,"height":235}},"56":{"xOffset":0,"yOffset":0,"xAdvance":140,"rect":{"x":1120,"y":0,"width":140,"height":235}},"57":{"xOffset":0,"yOffset":0,"xAdvance":140,"rect":{"x":1260,"y":0,"width":140,"height":235}}},"kerningDict":{}}]],0,0,[0],[9],[9]],[[{"name":"手機板面","rect":[0,0,1440,2560],"offset":[0,0],"originalSize":[1440,2560],"capInsets":[0,0,0,0]}],[0],0,[0],[2],[10]],[[{"name":"半透明黑窗","rect":[0,0,4096,2300],"offset":[0,0],"originalSize":[4096,2300],"capInsets":[0,0,0,0]}],[0],0,[0],[2],[11]],[[{"name":"機會記錄版","rect":[0,0,1115,204],"offset":[0,0],"originalSize":[1115,204],"capInsets":[0,0,0,0]}],[0],0,[0],[2],[12]],[[{"name":"得獎懸浮窗","rect":[0,0,876,1234],"offset":[0,0],"originalSize":[876,1234],"capInsets":[0,0,0,0]}],[0],0,[0],[2],[13]],[[{"name":"default_btn_disabled","rect":[0,0,40,40],"offset":[0,0],"originalSize":[40,40],"capInsets":[12,12,12,12]}],[0],0,[0],[2],[14]],[[{"name":"金色數字01","rect":[15,10,1372,215],"offset":[1,0],"originalSize":[1400,235],"capInsets":[0,0,0,0]}],[0],0,[0],[2],[15]],[[{"name":"扇形","rect":[0,13,280,269],"offset":[0,-4.5],"originalSize":[280,286],"capInsets":[0,0,0,0]}],[0],0,[0],[2],[16]],[[{"name":"得獎_叉叉","rect":[0,0,164,164],"offset":[0,0],"originalSize":[164,164],"capInsets":[0,0,0,0]}],[0],0,[0],[2],[17]],[[{"name":"輪盤內圈","rect":[203,303,1040,1040],"offset":[3,0],"originalSize":[1440,1646],"capInsets":[0,0,0,0]}],[0],0,[0],[2],[18]],[[{"name":"得獎懸浮窗_06","rect":[0,0,738,182],"offset":[0,0],"originalSize":[738,182],"capInsets":[0,0,0,0]}],[0],0,[0],[2],[19]],[[{"name":"B4BE802262","rect":[0,0,549,523],"offset":[0,0],"originalSize":[549,523],"capInsets":[0,0,0,0]}],[0],0,[0],[2],[20]],[[{"name":"手機黑文字框","rect":[0,0,1309,341],"offset":[0,0],"originalSize":[1309,341],"capInsets":[0,0,0,0]}],[0],0,[0],[2],[21]],[[{"name":"default_sprite_splash","rect":[0,0,2,2],"offset":[0,0],"originalSize":[2,2],"capInsets":[0,0,0,0]}],[0],0,[0],[2],[22]],[[{"name":"禮物外框","rect":[0,0,126,126],"offset":[0,0],"originalSize":[126,126],"capInsets":[0,0,0,0]}],[0],0,[0],[2],[23]],[[{"name":"go小圖標 (2)","rect":[0,0,138,139],"offset":[0,0],"originalSize":[138,139],"capInsets":[0,0,0,0]}],[0],0,[0],[2],[24]],[[{"name":"手機下裝飾","rect":[0,0,1440,38],"offset":[0,0],"originalSize":[1440,38],"capInsets":[0,0,0,0]}],[0],0,[0],[2],[25]],[[[15,"Guest1_Weel",null],[16,"畫布","81ZUbc/YhMLalIaIeW9zpW",[-16,-17,-18,-19,-20,-21,-22,-23,-24,-25,-26],[[30,true,-1,[5,1440,2560]],[31,45,-2],[33,-14,-13,-12,-11,-10,-9,-8,-7,-6,-5,-4,-3],[34,-15]],[5,1440,2560],[720,1280,0,0,0,0,1,1,1,1]],[17,"獎項",[-27,-28,-29,-30,-31,-32,-33,-34],[0,-43.896,0,0,0,0,1,1,1,1.42857]],[18,"警告",false,191,1,[-37,-38,-39],[[2,0,-35,[112],113],[37,-36]],[4,4281940281],[5,1444.7,2572],[-1.1,2,0,0,0,0,1,1,1,1]],[19,"得獎懸浮窗",[-41,-42,-43,-44],[[0,-40,[101],102]],[5,876,1234],[0,0,0,0,0,0,1,0,0,1]],[20,"輪盤",1,[-45,-46,-47,-48],[0,246.18,0,0,0,0,1,1,1,1]],[9,"獎項1",2,[-51,-52],[[6,"50",80,80,1,1,1,2,-49,[9]],[7,3,-50,[4,4278190080]]],[4,4287092213],[5,270,111],[169,431,0,0,0,-0.21405342901396007,0.9768219538520648,1,1,1],[1,0,0,-24.72]],[9,"獎項2",2,[-55,-56],[[6,"100",80,80,1,1,1,2,-53,[17]],[7,3,-54,[4,4278190080]]],[4,4287092213],[5,270,111],[385.044,220.548,0,0,0,-0.5520097534762494,0.8338376533037414,1,1,1],[1,0,0,-67.00999999999999]],[9,"獎項3",2,[-59,-60],[[6,"150",80,80,1,1,1,2,-57,[25]],[7,3,-58,[4,4278190080]]],[4,4287092213],[5,270,111],[389.712,-113.469,0,0,0,-0.8466950142898625,0.5320785212510363,1,1,1],[1,0,0,-115.708]],[9,"獎項4",2,[-63,-64],[[6,"200",80,80,1,1,1,2,-61,[33]],[7,3,-62,[4,4278190080]]],[4,4287092213],[5,270,111],[163.568,-337.511,0,0,0,-0.97974685547146,0.20024010385980628,1,1,1],[1,0,0,-156.898]],[9,"獎項5",2,[-67,-68],[[6,"250",80,80,1,1,1,2,-65,[41]],[7,3,-66,[4,4278190080]]],[4,4287092213],[5,270,111],[-155.031,-339.568,0,0,0,-0.9777978685121798,-0.2095503002456406,1,1,1],[1,0,0,-204.192]],[9,"獎項6",2,[-71,-72],[[6,"300",80,80,1,1,1,2,-69,[49]],[7,3,-70,[4,4278190080]]],[4,4287092213],[5,270,111],[-388.523,-105.027,0,0,0,-0.8381902021547493,-0.5453780202866454,1,1,1],[1,0,0,-246.101]],[9,"獎項7",2,[-75,-76],[[6,"350",80,80,1,1,1,2,-73,[57]],[7,3,-74,[4,4278190080]]],[4,4287092213],[5,270,111],[-384.634,211.257,0,0,0,-0.5843417320252725,-0.8115076957205671,1,1,1],[1,0,0,-288.487]],[9,"獎項8",2,[-79,-80],[[6,"400",80,80,1,1,1,2,-77,[65]],[7,3,-78,[4,4278190080]]],[4,4287092213],[5,270,111],[-157.878,436.661,0,0,0,0.22126766558224173,0.9752131152562424,1,1,1],[1,0,0,25.567]],[21,"Background",512,[-83],[[35,1,0,-81,[115],116],[32,0,45,100,40,-82]],[5,266,152],[100.11110025157924,-157.97985073255563,0,0,0,0,1,1,1,1]],[1,"輪盤_內",5,[2],[[0,-84,[66],67]],[5,1040,1040],[0,54.898,0,0,0,0,1,1,1,1]],[1,"輪盤_外",5,[-86],[[42,"default",0,"Roll",-85,[70],71]],[5,2424,2308.82],[0,61.837,0,0,0,0,1,0.7,0.7,1]],[1,"Title",5,[-88],[[11,"default","Usuall",0,"Usuall",-87,[76],77]],[5,1325.71,638.92],[0,-195.224,0,0,0,0,1,1,1,1]],[22,"半透明黑窗",false,1,[4],[[2,0,-89,[103],104]],[5,1440,2560]],[5,"得獎_中央圖標",4,[-91,-92],[[36,-90,[99]]],[5,753,808]],[1,"獎品照片框",6,[-94],[[0,-93,[5],6]],[5,126,126],[0,-133.116,0,0,0,0,1,1,1,1]],[5,"遮罩",20,[-96],[[8,1,0,-95,[4]]],[5,105,105]],[1,"獎品照片框",7,[-98],[[0,-97,[13],14]],[5,126,126],[6.058,-142.645,0,0,0,0,1,1,1,1]],[5,"遮罩",22,[-100],[[8,1,0,-99,[12]]],[5,105,105]],[1,"獎品照片框",8,[-102],[[0,-101,[21],22]],[5,126,126],[3.683,-136.879,0,0,0,0,1,1,1,1]],[5,"遮罩",24,[-104],[[8,1,0,-103,[20]]],[5,105,105]],[1,"獎品照片框",9,[-106],[[0,-105,[29],30]],[5,126,126],[-4.084,-140.056,0,0,0,0,1,1,1,1]],[5,"遮罩",26,[-108],[[8,1,0,-107,[28]]],[5,105,105]],[1,"獎品照片框",10,[-110],[[0,-109,[37],38]],[5,126,126],[4.289,-140.682,0,0,0,0,1,1,1,1]],[5,"遮罩",28,[-112],[[8,1,0,-111,[36]]],[5,105,105]],[1,"獎品照片框",11,[-114],[[0,-113,[45],46]],[5,126,126],[-6.337,-144.121,0,0,0,0,1,1,1,1]],[5,"遮罩",30,[-116],[[8,1,0,-115,[44]]],[5,105,105]],[1,"獎品照片框",12,[-118],[[0,-117,[53],54]],[5,126,126],[-10.845,-142.985,0,0,0,0,1,1,1,1]],[5,"遮罩",32,[-120],[[8,1,0,-119,[52]]],[5,105,105]],[1,"獎品照片框",13,[-122],[[0,-121,[61],62]],[5,126,126],[1.472,-139.688,0,0,0,0,1,1,1,1]],[5,"遮罩",34,[-124],[[8,1,0,-123,[60]]],[5,105,105]],[3,"Light(EX)",16,[[11,"default","usual",0,"usual",-125,[68],69]],[5,2031.62,1467.23],[0,4.06857,0,0,0,0,1,1,1,1]],[3,"go按鈕",5,[[0,-126,[72],73],[45,3,-127,[[13,"231fb6ZVWNN944v7V0dlDwZ","StartBtn",1]]]],[5,286,286],[0,59.531,0,0,0,0,1,0.7,0.7,0]],[3,"指針",17,[[43,"default",0,-128,[74],75]],[5,259.55,323.35],[0,267.373,0,0,0,0,1,0.7,0.7,1]],[3,"LightIO",1,[[44,"default","usual",0,false,"usual",1,-129,[78],79]],[5,2300,2273.22],[0,291.778,0,0,0,0,1,0.7,0.7,1]],[1,"手機黑文字框",1,[-131],[[0,-130,[83],84]],[5,1309,341],[0,-622.729,0,0,0,0,1,1,1,1]],[1,"規則",40,[-133],[[38,"按下輪盤上的         進行抽獎，大獎開不完!!",70,120,1,-132,[82]]],[5,1145,304],[-7.328,-38.606,0,0,0,0,1,1,1,1]],[1,"機會記錄版",1,[-135],[[0,-134,[86],87]],[5,1115,204],[0,-996.053,0,0,0,0,1,1,1,1]],[3,"得獎關閉",4,[[0,-136,[90],91],[46,-137,[[47,"231fb6ZVWNN944v7V0dlDwZ","closeFuc","prize"]]]],[5,164,164],[0,-747.436,0,0,0,0,1,1,1,1]],[1,"遮罩",19,[-139],[[8,1,0,-138,[96]]],[5,740,740],[0,-16.131,0,0,0,0,1,0.8,0.8,1]],[23,"獎項",4,[[6,"IPHONE",100,100,1,1,1,2,-140,[100]],[7,3,-141,[4,4278190080]]],[4,4294770301],[5,846,208],[-1,-499,0,0,0,0,1,1,1,1]],[3,"關閉",3,[[12,2,-143,[[48,"231fb6ZVWNN944v7V0dlDwZ","closeFuc","alret",1]],[4,4293322470],[4,4291348680],[4,3363338360],-142,108,109,110,111]],[5,63,58],[542.044,96.608,0,0,0,0,1,1,1,1]],[24,"New Button",false,1,[14],[[12,2,-144,[[13,"231fb6ZVWNN944v7V0dlDwZ","lettorey",1]],[4,4293322470],[4,4291348680],[4,3363338360],14,117,118,119,120]],[5,266,152],[0,0.12364248025722088,1.5393411232404977],[356,-632,0,0,0,0,1,1,1,1]],[25,"不可觸碰布",false,0,1,[[2,0,-145,[121],122]],[5,1440,2560]],[49,"New Node",[1],[0,0,0],[0,0,0,0,0,0,1,1,1,1]],[26,"Main Camera",1,[[50,7,-1,-146]]],[4,"背景",1,[[0,-147,[0],1]],[5,1440,2560]],[4,"獎品照片",21,[[2,0,-148,[2],3]],[5,105,105]],[10,"扇形",0,6,[[0,-149,[7],8]],[5,280,269],[-2.976,-124.257,0,0,0,0.019310867770493016,0.9998135278070359,1.38,1.62,1],[1,0,0,2.213]],[4,"獎品照片",23,[[2,0,-150,[10],11]],[5,105,105]],[10,"扇形",0,7,[[0,-151,[15],16]],[5,280,269],[11.172,-125.332,0,0,0,-0.009171576632193867,0.9999579402065267,1.38,1.62,1.38],[1,0,0,-1.0509999999999997]],[4,"獎品照片",25,[[2,0,-152,[18],19]],[5,105,105]],[10,"扇形",0,8,[[0,-153,[23],24]],[5,280,269],[6.898,-125.178,0,0,0,0.0174960330064036,0.9998469326997202,1.38,1.62,1.38],[1,0,0,2.005]],[4,"獎品照片",27,[[2,0,-154,[26],27]],[5,105,105]],[10,"扇形",0,9,[[0,-155,[31],32]],[5,280,269],[3.044,-124.556,0,0,0,-0.008778893370243998,0.9999614647731151,1.38,1.62,1.38],[1,0,0,-1.006]],[4,"獎品照片",29,[[2,0,-156,[34],35]],[5,105,105]],[10,"扇形",0,10,[[0,-157,[39],40]],[5,280,269],[6.884,-124.049,0,0,0,0.010559045753985644,0.9999442517224474,1.38,1.62,1.38],[1,0,0,1.2100000000000002]],[4,"獎品照片",31,[[2,0,-158,[42],43]],[5,105,105]],[10,"扇形",0,11,[[0,-159,[47],48]],[5,280,269],[-7.839,-124.013,0,0,0,-0.00287106267515401,0.9999958784910643,1.38,1.62,1.38],[1,0,0,-0.32899999999999974]],[4,"獎品照片",33,[[2,0,-160,[50],51]],[5,105,105]],[10,"扇形",0,12,[[0,-161,[55],56]],[5,280,269],[-17.432,-123.815,0,0,0,-0.036887889601141345,0.9993194101991485,1.38,1.62,1.38],[1,0,0,-4.228]],[4,"獎品照片",35,[[2,0,-162,[58],59]],[5,105,105]],[27,"扇形",false,13,[[0,-163,[63],64]],[5,280,269],[-14.613,-123.655,0,0,0,-0.025836724219999326,0.9996661761215989,1.38,1.62,1.38],[1,0,0,-2.9610000000000003]],[3,"go小圖標 (2)",41,[[0,-164,[80],81]],[5,138,139],[-65.459,119.503,0,0,0,0,1,1,1,1]],[29,"機會次數",42,[-165],[5,116.9,82.4],[-2.834,2.807,0,0,0,0,1,1,1,1]],[39,"20",206.8,206.8,false,1,1,2,69,[85]],[3,"手機下裝飾",1,[[0,-166,[88],89]],[5,1440,38],[0,-1260.545,0,0,0,0,1,1,1,1]],[3,"得獎懸浮窗_06",4,[[0,-167,[92],93]],[5,738,182],[0,465.094,0,0,0,0,1,1,1,1]],[4,"獎品照片",44,[[2,0,-168,[94],95]],[5,740,740]],[3,"頭相框",19,[[11,"default","animation",0,"animation",-169,[97],98]],[5,1049,1049],[0,-16.131,0,0,0,0,1,0.8,0.8,1]],[4,"警告圖示",3,[[0,-170,[105],106]],[5,1216,312]],[3,"警告文字",3,[[40,"沒有次數了，無法抽獎",80,80,1,1,2,-171,[107]]],[5,899,263],[60,-7,0,0,0,0,1,1,1,1]],[28,"Label",512,14,[[41,"button",20,false,1,1,1,1,-172,[114]]],[4,4278190080],[5,100,40]]],0,[0,0,1,0,0,1,0,10,2,0,11,48,0,12,3,0,13,70,0,14,18,0,15,36,0,16,38,0,17,39,0,18,17,0,19,16,0,20,15,0,0,1,0,0,1,0,-1,50,0,-2,51,0,-3,5,0,-4,39,0,-5,40,0,-6,42,0,-7,71,0,-8,18,0,-9,3,0,-10,47,0,-11,48,0,-1,6,0,-2,7,0,-3,8,0,-4,9,0,-5,10,0,-6,11,0,-7,12,0,-8,13,0,0,3,0,0,3,0,-1,75,0,-2,76,0,-3,46,0,0,4,0,-1,43,0,-2,72,0,-3,19,0,-4,45,0,-1,15,0,-2,16,0,-3,37,0,-4,17,0,0,6,0,0,6,0,-1,20,0,-2,53,0,0,7,0,0,7,0,-1,22,0,-2,55,0,0,8,0,0,8,0,-1,24,0,-2,57,0,0,9,0,0,9,0,-1,26,0,-2,59,0,0,10,0,0,10,0,-1,28,0,-2,61,0,0,11,0,0,11,0,-1,30,0,-2,63,0,0,12,0,0,12,0,-1,32,0,-2,65,0,0,13,0,0,13,0,-1,34,0,-2,67,0,0,14,0,0,14,0,-1,77,0,0,15,0,0,16,0,-1,36,0,0,17,0,-1,38,0,0,18,0,0,19,0,-1,44,0,-2,74,0,0,20,0,-1,21,0,0,21,0,-1,52,0,0,22,0,-1,23,0,0,23,0,-1,54,0,0,24,0,-1,25,0,0,25,0,-1,56,0,0,26,0,-1,27,0,0,27,0,-1,58,0,0,28,0,-1,29,0,0,29,0,-1,60,0,0,30,0,-1,31,0,0,31,0,-1,62,0,0,32,0,-1,33,0,0,33,0,-1,64,0,0,34,0,-1,35,0,0,35,0,-1,66,0,0,36,0,0,37,0,0,37,0,0,38,0,0,39,0,0,40,0,-1,41,0,0,41,0,-1,68,0,0,42,0,-1,69,0,0,43,0,0,43,0,0,44,0,-1,73,0,0,45,0,0,45,0,21,46,0,0,46,0,0,47,0,0,48,0,0,50,0,0,51,0,0,52,0,0,53,0,0,54,0,0,55,0,0,56,0,0,57,0,0,58,0,0,59,0,0,60,0,0,61,0,0,62,0,0,63,0,0,64,0,0,65,0,0,66,0,0,67,0,0,68,0,-1,70,0,0,71,0,0,72,0,0,73,0,0,74,0,0,75,0,0,76,0,0,77,0,22,49,1,4,49,2,4,15,4,4,18,14,4,47,172],[0,0,0,0,0,0,0,0,0,0,0,0,0,0,0,0,0,0,0,0,0,0,0,0,0,0,0,0,0,0,0,0,0,0,0,0,0,0,0,0,0,0,0,0,0,0,0,0,0,0,0,0,0,0,0,0,0,0,0,0,0,0,0,0,0,0,0,0,0,0,0,0,0,0,0,0,0,0,0,0,0,0,0,0,0,0,0,0,0,0,0,0,0,0,0,0,0,0,0,0,0,0,0,0,0,0,0,0,0,0,0,0,0,0,0,0,0,0,0,0,0,0,0,70],[-1,1,-1,1,-1,-1,1,-1,1,-1,-1,1,-1,-1,1,-1,1,-1,-1,1,-1,-1,1,-1,1,-1,-1,1,-1,-1,1,-1,1,-1,-1,1,-1,-1,1,-1,1,-1,-1,1,-1,-1,1,-1,1,-1,-1,1,-1,-1,1,-1,1,-1,-1,1,-1,-1,1,-1,1,-1,-1,1,-1,3,-1,3,-1,1,-1,3,-1,3,-1,3,-1,1,-1,-1,1,-1,-1,1,-1,1,-1,1,-1,1,-1,1,-1,-1,3,-1,-1,-1,1,-1,1,-1,1,-1,5,6,7,8,-1,1,-1,-1,1,5,6,7,8,-1,1,23],[0,26,0,1,0,0,2,0,3,0,0,1,0,0,2,0,3,0,0,1,0,0,2,0,3,0,0,1,0,0,2,0,3,0,0,1,0,0,2,0,3,0,0,1,0,0,2,0,3,0,0,1,0,0,2,0,3,0,0,1,0,0,2,0,3,0,0,27,4,28,4,29,0,30,4,31,4,32,4,33,0,34,0,0,35,0,0,36,0,37,0,38,0,39,0,1,0,4,40,0,0,0,41,0,42,0,43,0,5,6,5,7,0,8,0,0,5,5,6,5,7,0,8,44]],[[{"name":"警告2","rect":[2,2,1216,312],"offset":[0,0],"originalSize":[1220,316],"capInsets":[0,0,0,0]}],[0],0,[0],[2],[45]],[[{"name":"go按鈕","rect":[0,0,286,286],"offset":[0,0],"originalSize":[286,286],"capInsets":[0,0,0,0]}],[0],0,[0],[2],[46]],[[{"name":"default_btn_pressed","rect":[0,0,40,40],"offset":[0,0],"originalSize":[40,40],"capInsets":[12,12,12,12]}],[0],0,[0],[2],[47]],[[{"name":"default_btn_normal","rect":[0,0,40,40],"offset":[0,0],"originalSize":[40,40],"capInsets":[12,12,12,12]}],[0],0,[0],[2],[48]]]]