[1,["ecpdLyjvZBwrvm+cedCcQy","06cOWTHEJIvoS01V/ze0z+","7a/QZLET9IDreTiBfRn2PD","a2MjXRFdtLlYQ5ouAFv/+R","bdEi0jI7NMu6xBTWOz0ufd","c5wR363ZZAULCimb3ZROwZ","f6M45OywpLsYT/N7kExEWa","aaeaW/8OxJBpHq92oEaTG3","02delMVqdBD70a/HSD99FK","26bsrEgc9HlpZj2+BmIi78","9cx4nsalZIH6hq2avBH4G5","aaaLWkOxhHCaF5Ivetx8WC","55hQlgwbtEgoKD5utrTb9O","a5Pqq6ZPRId45od1w6P7Di","5bpuhtUZtCy5SmA/3/uETz","21Bp713thHFIr6/TENb6Qp","a9dj211k1MfqPgdk0ekLMP","aawyqGWudNWpcfmDH8JFsE","56D69JIXRDra6qusxDGQup"],["node","_spriteFrame","_textureSetter","_parent","_N$skeletonData","scene"],["cc.SpriteFrame",["cc.Node",["_name","_id","_components","_contentSize","_parent","_trs","_children","_eulerAngles","_color","_anchorPoint"],1,9,5,1,7,2,5,5,5],["cc.Sprite",["_sizeMode","node","_materials","_spriteFrame"],2,1,3,6],["sp.SkeletonData",["_name","_atlasText","textureNames","_skeletonJson","textures"],-1,3],["cc.SceneAsset",["_name","asyncLoadAssets"],1],["cc.Canvas",["_fitWidth","node","_designResolution"],2,1,5],["cc.Widget",["_alignFlags","node"],2,1],["6dc05RqXWxMa4vuAhRC6dsu",["node"],3,1],["47ce2xxDsBPgqV10snO3sxM",["node"],3,1],["89209mb7B5E7opQmXjzQ00M",["node"],3,1],["sp.Skeleton",["defaultSkin","defaultAnimation","_preCacheMode","_animationName","node","_materials","_N$skeletonData"],-1,1,3,6],["cc.Scene",["_name","_children","_anchorPoint","_trs"],2,2,5,7],["cc.Camera",["_clearFlags","_depth","node"],1,1]],[[1,0,4,2,3,5,2],[2,1,2,3,1],[9,0,1],[2,0,1,2,3,2],[1,0,4,2,8,3,9,5,2],[10,0,1,2,3,4,5,6,5],[3,0,1,2,3,4,5],[4,0,1,3],[1,0,6,2],[1,0,1,6,2,3,5,3],[1,0,4,2,3,5,7,2],[1,0,4,2,2],[1,0,4,2,3,2],[5,0,1,2,2],[6,0,1,2],[7,0,1],[8,0,1],[11,0,1,2,3,2],[12,0,1,2,3]],[[[{"name":"紅包3","rect":[0,2,382,812],"offset":[-1.5,0],"originalSize":[385,816],"capInsets":[0,0,0,0]}],[0],0,[0],[2],[4]],[[{"name":"背景","rect":[0,0,4096,2376],"offset":[0,0],"originalSize":[4096,2376],"capInsets":[0,0,0,0]}],[0],0,[0],[2],[5]],[[{"name":"上方框","rect":[0,0,1440,190],"offset":[0,4.5],"originalSize":[1440,199],"capInsets":[0,0,0,0]}],[0],0,[0],[2],[6]],[[{"name":"紅包2","rect":[2,2,497,594],"offset":[1,-0.5],"originalSize":[499,597],"capInsets":[0,0,0,0]}],[0],0,[0],[2],[7]],[[{"name":"default_sprite_splash","rect":[0,0,2,2],"offset":[0,0],"originalSize":[2,2],"capInsets":[0,0,0,0]}],[0],0,[0],[2],[8]],[[{"name":"背景-直","rect":[0,0,1440,2560],"offset":[0,0],"originalSize":[1440,2560],"capInsets":[0,0,0,0]}],[0],0,[0],[2],[9]],[[{"name":"遊戲即將開始","rect":[3,2,1306,371],"offset":[-2,4],"originalSize":[1316,383],"capInsets":[0,0,0,0]}],[0],0,[0],[2],[10]],[[[6,"button2","\nbutton.png\nsize: 536,1740\nformat: RGBA8888\nfilter: Linear,Linear\nrepeat: none\n1button\n  rotate: true\n  xy: 2, 2\n  size: 503, 529\n  orig: 510, 534\n  offset: 3, 2\n  index: -1\n2button\n  rotate: false\n  xy: 2, 1009\n  size: 525, 404\n  orig: 532, 553\n  offset: 4, 3\n  index: -1\n3button\n  rotate: false\n  xy: 2, 507\n  size: 523, 500\n  orig: 531, 504\n  offset: 4, 1\n  index: -1\nlight\n  rotate: false\n  xy: 2, 1609\n  size: 186, 126\n  orig: 200, 126\n  offset: 7, 0\n  index: -1\nword\n  rotate: false\n  xy: 190, 1562\n  size: 337, 173\n  orig: 416, 182\n  offset: 39, 5\n  index: -1\nword2\n  rotate: false\n  xy: 2, 1415\n  size: 406, 145\n  orig: 416, 182\n  offset: 5, 18\n  index: -1\n",["button.png"],{"skeleton":{"hash":"U4GfeDyJGsoX4PRCimxpxjWcDFo","spine":"3.8.99","x":-279.2,"y":-363.64,"width":532,"height":608,"images":"../動態 - 壓縮/按鈕/","audio":""},"bones":[{"name":"root"},{"name":"1button","parent":"root","y":50.46},{"name":"light","parent":"root","rotation":-13.24,"x":-538.22,"y":-1.61},{"name":"word","parent":"root","y":33.08},{"name":"word2","parent":"root","y":33.08}],"slots":[{"name":"3button","bone":"root","attachment":"3button"},{"name":"cut","bone":"root","attachment":"cut"},{"name":"1button","bone":"1button","attachment":"1button"},{"name":"2button","bone":"root","attachment":"2button"},{"name":"cut2","bone":"root","attachment":"cut2"},{"name":"light","bone":"light","attachment":"light","blend":"additive"},{"name":"word","bone":"word","attachment":"word2"},{"name":"word2","bone":"word2","attachment":"word2"}],"skins":[{"name":"default","attachments":{"1button":{"1button":{"x":-9.2,"y":-73.1,"width":510,"height":534}},"2button":{"2button":{"x":-13.2,"y":-87.14,"width":532,"height":553}},"3button":{"3button":{"x":-12.7,"y":-65.64,"width":531,"height":504}},"cut":{"cut":{"type":"clipping","end":"1button","vertexCount":11,"color":"ce3a3aff","vertices":[-284.62,36.13,-219.36,-123.26,-169.16,-209.85,-100.13,-275.11,-0.99,-302.72,100.67,-250.01,174.71,-155.89,268.84,52.44,236.21,255.75,-90.09,303.44,-284.62,191.75]}},"cut2":{"cut2":{"type":"clipping","end":"light","vertexCount":89,"color":"ce3a3aff","vertices":[-254.72,8.62,-255.63,-14.74,-254.26,-35.81,-246.93,-74.28,-232.28,-115.5,-211.67,-159.01,-183.19,-203.04,-148.86,-247.38,-122.57,-274.41,-91.57,-298.96,-65.53,-312.85,-43.71,-319.55,-27.09,-322.03,-6.26,-321.28,12.09,-319.05,33.18,-312.32,58.08,-298.37,85.64,-278.45,111.87,-253.89,146.06,-210.85,175.28,-170.02,200.84,-124.53,216.11,-89.34,227.61,-21.79,221.24,88.62,209.45,122.26,192.8,149.52,172.35,172.18,146.91,193.37,118.44,210.2,83.77,224,48.22,233.91,4.28,239.19,-34.45,238.9,-68.03,233.9,-99.88,225.69,-123.5,216.28,-143.51,207.14,-163.37,194.61,-186.74,175.89,-207.03,153.43,-224.88,127.46,-236.55,96.93,-240.27,72.36,-240.48,44.91,-232.85,11.77,-220.37,-17.94,-199.26,-51.27,-178.44,-76.96,-158.09,-95.78,-136.04,-114.83,-111.07,-131.19,-82.92,-145.92,-64.4,-151.95,-39.21,-157.45,3.01,-158.03,46.46,-148.81,85.36,-129.97,119.3,-107.53,147.09,-83.31,165.21,-65.09,185.7,-39.44,202.98,-11.08,215.42,16.96,219.34,34.26,223,56.52,227.6,-21.81,224.65,-36.45,210.69,-76.88,188.23,-118.57,161.01,-157.01,132.88,-190.04,101.13,-220.06,72.83,-241.88,44.54,-257.86,25.75,-265.2,-2.33,-270.6,-19.42,-272.12,-47.28,-268.23,-63.7,-262.83,-85.67,-252.45,-105.76,-239.92,-131.25,-220.7,-161.49,-189.16,-185.06,-159.64,-212.49,-119.46,-231.07,-81.88,-243.59,-50.77,-250.72,-25.07]}},"light":{"light":{"x":1.94,"y":60.04,"scaleX":3.1514,"scaleY":5.0911,"rotation":-4.78,"width":200,"height":126}},"word":{"word":{"x":-10.27,"y":22.58,"scaleX":1.0436,"scaleY":1.0436,"width":416,"height":182},"word2":{"x":-10.27,"y":13.24,"scaleX":1.0436,"scaleY":1.0436,"width":416,"height":182}},"word2":{"word":{"x":-10.27,"y":22.58,"scaleX":1.0436,"scaleY":1.0436,"width":416,"height":182},"word2":{"x":-10.27,"y":13.24,"scaleX":1.0436,"scaleY":1.0436,"width":416,"height":182}}}}],"animations":{"animation":{"slots":{"light":{"color":[{"time":0.1667,"color":"ffffff00"},{"time":0.5333,"color":"fffb573d"},{"time":1,"color":"ffffff00"}]},"word":{"attachment":[{"name":null}]},"word2":{"attachment":[{"name":null}]}},"bones":{"1button":{"translate":[{"time":0.3333},{"time":0.4333,"y":-20.6},{"time":0.6667,"curve":"stepped"},{"time":1},{"time":1.1,"y":-20.6},{"time":1.3333}]},"light":{"translate":[{"time":0.1667},{"time":1,"x":973.94,"y":-224.8}]}},"deform":{"default":{"cut2":{"cut2":[{"time":0.3333},{"time":0.4333,"offset":49,"vertices":[-20.54404,0,-20.54404,0,-20.54404,0,-20.54404,0,-20.54404,0,-20.54404,0,-20.54404,0,-20.54404,0,-20.54404,0,-20.54404,0,-20.54404,0,-20.54404,0,-20.54404,0,-20.54404,0,-20.54404,0,-20.54404,0,-20.54404,0,-20.54404,0,-20.54404,0,-20.54404,0,-20.54404,0,-20.54404,0,-20.54404,0,-20.54404,0,-20.54404,0,-20.54404,0,-20.54404,0,-20.54404,0,-20.54404,0,-20.54404,0,-20.54404,0,-20.54404,0,-20.54404,0,-20.54404,0,-20.54404,0,-20.54404,0,-20.54404,0,-20.54404,0,-20.54404,0,-20.54404,0,-20.54404,0,-20.54404]},{"time":0.6667}]}}}},"animation2":{"slots":{"light":{"color":[{"time":0.1667,"color":"ffffff00"},{"time":0.5333,"color":"fffb573d"},{"time":1,"color":"ffffff00"}]},"word":{"attachment":[{"name":"word"}]},"word2":{"color":[{"color":"ffffff00"},{"time":0.1667,"color":"ffffffb3"},{"time":0.6667,"color":"ffffff00"}],"attachment":[{"name":"word"}]}},"bones":{"1button":{"translate":[{"time":0.3333},{"time":0.4333,"y":-20.6},{"time":0.6667,"curve":"stepped"},{"time":1},{"time":1.1,"y":-20.6},{"time":1.3333}]},"light":{"translate":[{"time":0.1667},{"time":1,"x":973.94,"y":-224.8}]},"word":{"translate":[{"time":0.3333},{"time":0.4333,"y":-20.6},{"time":0.6667,"curve":"stepped"},{"time":1},{"time":1.1,"y":-20.6},{"time":1.3333}]},"word2":{"translate":[{"time":0.3333},{"time":0.4333,"y":-20.6},{"time":0.6667,"curve":"stepped"},{"time":1},{"time":1.1,"y":-20.6},{"time":1.3333}],"scale":[{},{"time":0.6667,"x":1.298,"y":1.298}]}},"deform":{"default":{"cut2":{"cut2":[{"time":0.3333},{"time":0.4333,"offset":49,"vertices":[-20.54404,0,-20.54404,0,-20.54404,0,-20.54404,0,-20.54404,0,-20.54404,0,-20.54404,0,-20.54404,0,-20.54404,0,-20.54404,0,-20.54404,0,-20.54404,0,-20.54404,0,-20.54404,0,-20.54404,0,-20.54404,0,-20.54404,0,-20.54404,0,-20.54404,0,-20.54404,0,-20.54404,0,-20.54404,0,-20.54404,0,-20.54404,0,-20.54404,0,-20.54404,0,-20.54404,0,-20.54404,0,-20.54404,0,-20.54404,0,-20.54404,0,-20.54404,0,-20.54404,0,-20.54404,0,-20.54404,0,-20.54404,0,-20.54404,0,-20.54404,0,-20.54404,0,-20.54404,0,-20.54404,0,-20.54404]},{"time":0.6667}]}}}},"animation3":{"slots":{"light":{"color":[{"time":0.1,"color":"ffffff00"},{"time":0.2667,"color":"fffb573d"},{"time":0.5,"color":"ffffff00","curve":"stepped"},{"time":0.7667,"color":"ffffff00"},{"time":0.9333,"color":"fffb573d"},{"time":1.1667,"color":"ffffff00"}]}},"bones":{"1button":{"translate":[{},{"time":0.1,"y":-64.87},{"time":0.2},{"time":0.3,"y":-64.87},{"time":0.4},{"time":0.4667,"y":-64.87},{"time":0.5667},{"time":0.6667,"y":-64.87},{"time":0.7667},{"time":0.8667,"y":-64.87},{"time":0.9667},{"time":1.0667,"y":-64.87},{"time":1.1667},{"time":1.2333,"y":-64.87},{"time":1.3333}]},"light":{"translate":[{"time":0.1},{"time":0.5,"x":973.94,"y":-224.8},{"time":0.7667},{"time":1.1667,"x":973.94,"y":-224.8}]},"word":{"translate":[{},{"time":0.1,"y":-64.87},{"time":0.2},{"time":0.3,"y":-64.87},{"time":0.4},{"time":0.4667,"y":-64.87},{"time":0.5667},{"time":0.6667,"y":-64.87},{"time":0.7667},{"time":0.8667,"y":-64.87},{"time":0.9667},{"time":1.0667,"y":-64.87},{"time":1.1667},{"time":1.2333,"y":-64.87},{"time":1.3333}]},"word2":{"translate":[{},{"time":0.1,"y":-64.87},{"time":0.2},{"time":0.3,"y":-64.87},{"time":0.4},{"time":0.4667,"y":-64.87},{"time":0.5667},{"time":0.6667,"y":-64.87},{"time":0.7667},{"time":0.8667,"y":-64.87},{"time":0.9667},{"time":1.0667,"y":-64.87},{"time":1.1667},{"time":1.2333,"y":-64.87},{"time":1.3333}]}},"deform":{"default":{"cut2":{"cut2":[{},{"time":0.1,"offset":49,"vertices":[-65.32202,0,-65.32202,0,-65.32202,0,-65.32202,0,-65.32202,0,-65.32202,0,-65.32202,0,-65.32202,0,-65.32202,0,-65.32202,0,-65.32202,0,-65.32202,0,-65.32202,0,-65.32202,0,-65.32202,0,-65.32202,0,-65.32202,0,-65.32202,0,-65.32202,0,-65.32202,0,-65.32202,0,-65.32202,0,-65.32202,0,-65.32202,0,-65.32202,0,-65.32202,0,-65.32202,0,-65.32202,0,-65.32202,0,-65.32202,0,-65.32202,0,-65.32202,0,-65.32202,0,-65.32202,0,-65.32202,0,-65.32202,0,-65.32202,0,-65.32202,0,-65.32202,0,-65.32202,0,-65.32202,0,-65.32202]},{"time":0.2},{"time":0.3,"offset":49,"vertices":[-65.32202,0,-65.32202,0,-65.32202,0,-65.32202,0,-65.32202,0,-65.32202,0,-65.32202,0,-65.32202,0,-65.32202,0,-65.32202,0,-65.32202,0,-65.32202,0,-65.32202,0,-65.32202,0,-65.32202,0,-65.32202,0,-65.32202,0,-65.32202,0,-65.32202,0,-65.32202,0,-65.32202,0,-65.32202,0,-65.32202,0,-65.32202,0,-65.32202,0,-65.32202,0,-65.32202,0,-65.32202,0,-65.32202,0,-65.32202,0,-65.32202,0,-65.32202,0,-65.32202,0,-65.32202,0,-65.32202,0,-65.32202,0,-65.32202,0,-65.32202,0,-65.32202,0,-65.32202,0,-65.32202,0,-65.32202]},{"time":0.3667},{"time":0.4667,"offset":49,"vertices":[-65.32202,0,-65.32202,0,-65.32202,0,-65.32202,0,-65.32202,0,-65.32202,0,-65.32202,0,-65.32202,0,-65.32202,0,-65.32202,0,-65.32202,0,-65.32202,0,-65.32202,0,-65.32202,0,-65.32202,0,-65.32202,0,-65.32202,0,-65.32202,0,-65.32202,0,-65.32202,0,-65.32202,0,-65.32202,0,-65.32202,0,-65.32202,0,-65.32202,0,-65.32202,0,-65.32202,0,-65.32202,0,-65.32202,0,-65.32202,0,-65.32202,0,-65.32202,0,-65.32202,0,-65.32202,0,-65.32202,0,-65.32202,0,-65.32202,0,-65.32202,0,-65.32202,0,-65.32202,0,-65.32202,0,-65.32202]},{"time":0.5667},{"time":0.6667,"offset":49,"vertices":[-65.32202,0,-65.32202,0,-65.32202,0,-65.32202,0,-65.32202,0,-65.32202,0,-65.32202,0,-65.32202,0,-65.32202,0,-65.32202,0,-65.32202,0,-65.32202,0,-65.32202,0,-65.32202,0,-65.32202,0,-65.32202,0,-65.32202,0,-65.32202,0,-65.32202,0,-65.32202,0,-65.32202,0,-65.32202,0,-65.32202,0,-65.32202,0,-65.32202,0,-65.32202,0,-65.32202,0,-65.32202,0,-65.32202,0,-65.32202,0,-65.32202,0,-65.32202,0,-65.32202,0,-65.32202,0,-65.32202,0,-65.32202,0,-65.32202,0,-65.32202,0,-65.32202,0,-65.32202,0,-65.32202,0,-65.32202]},{"time":0.7667},{"time":0.8667,"offset":49,"vertices":[-65.32202,0,-65.32202,0,-65.32202,0,-65.32202,0,-65.32202,0,-65.32202,0,-65.32202,0,-65.32202,0,-65.32202,0,-65.32202,0,-65.32202,0,-65.32202,0,-65.32202,0,-65.32202,0,-65.32202,0,-65.32202,0,-65.32202,0,-65.32202,0,-65.32202,0,-65.32202,0,-65.32202,0,-65.32202,0,-65.32202,0,-65.32202,0,-65.32202,0,-65.32202,0,-65.32202,0,-65.32202,0,-65.32202,0,-65.32202,0,-65.32202,0,-65.32202,0,-65.32202,0,-65.32202,0,-65.32202,0,-65.32202,0,-65.32202,0,-65.32202,0,-65.32202,0,-65.32202,0,-65.32202,0,-65.32202]},{"time":0.9667},{"time":1.0667,"offset":49,"vertices":[-65.32202,0,-65.32202,0,-65.32202,0,-65.32202,0,-65.32202,0,-65.32202,0,-65.32202,0,-65.32202,0,-65.32202,0,-65.32202,0,-65.32202,0,-65.32202,0,-65.32202,0,-65.32202,0,-65.32202,0,-65.32202,0,-65.32202,0,-65.32202,0,-65.32202,0,-65.32202,0,-65.32202,0,-65.32202,0,-65.32202,0,-65.32202,0,-65.32202,0,-65.32202,0,-65.32202,0,-65.32202,0,-65.32202,0,-65.32202,0,-65.32202,0,-65.32202,0,-65.32202,0,-65.32202,0,-65.32202,0,-65.32202,0,-65.32202,0,-65.32202,0,-65.32202,0,-65.32202,0,-65.32202,0,-65.32202]},{"time":1.1333},{"time":1.2333,"offset":49,"vertices":[-65.32202,0,-65.32202,0,-65.32202,0,-65.32202,0,-65.32202,0,-65.32202,0,-65.32202,0,-65.32202,0,-65.32202,0,-65.32202,0,-65.32202,0,-65.32202,0,-65.32202,0,-65.32202,0,-65.32202,0,-65.32202,0,-65.32202,0,-65.32202,0,-65.32202,0,-65.32202,0,-65.32202,0,-65.32202,0,-65.32202,0,-65.32202,0,-65.32202,0,-65.32202,0,-65.32202,0,-65.32202,0,-65.32202,0,-65.32202,0,-65.32202,0,-65.32202,0,-65.32202,0,-65.32202,0,-65.32202,0,-65.32202,0,-65.32202,0,-65.32202,0,-65.32202,0,-65.32202,0,-65.32202,0,-65.32202]},{"time":1.3333}]}}}},"animation5":{"slots":{"light":{"color":[{"time":0.1667,"color":"ffffff00"},{"time":0.5333,"color":"fffb573d"},{"time":1,"color":"ffffff00"}]},"word":{"attachment":[{"name":null}]},"word2":{"attachment":[{"name":null}]}},"bones":{"light":{"translate":[{"time":0.1667},{"time":1,"x":973.94,"y":-224.8}]}}}}},[0]]],0,0,[0],[-1],[11]],[[[7,"Guest2_Wait",null],[8,"場景",[-1,-2,-3,-4,-5,-6,-7,-8,-9,-10,-11]],[9,"畫布","81ZUbc/YhMLalIaIeW9zpW",[-16,1],[[13,true,-12,[5,1440,2560]],[14,45,-13],[15,-14],[16,-15]],[5,1440,2560],[720,1280,0,0,0,0,1,1,1,1]],[0,"紅包2",1,[[1,-17,[4],5],[2,-18]],[5,497,594],[474.795,686.113,0,0,0,0,1,1,1,1]],[0,"紅包3",1,[[1,-19,[6],7],[2,-20]],[5,382,812],[-529.043,-637.268,0,0,0,0,1,1,1,1]],[0,"紅包3 copy",1,[[1,-21,[8],9],[2,-22]],[5,382,812],[538.702,-361.536,0,0,0,0,1,-1,1,1]],[10,"redbagface",1,[[5,"default","smile2",0,"smile2",-23,[10],11],[2,-24]],[5,278.12,1260.71],[-169.449,552.38,0,0,0,-0.13499792670426172,0.9908458809449383,2,2,1],[1,0,0,-15.517]],[17,"New Node",[2],[0,0,0],[0,0,0,0,0,0,1,1,1,1]],[11,"Main Camera",2,[[18,7,-1,-25]]],[0,"背景",1,[[3,0,-26,[0],1]],[5,4096,2565],[0,3,0,0,0,0,1,1,1,1]],[12,"背景-直",1,[[1,-27,[2],3]],[5,1440,2560]],[0,"遊戲即將開始",1,[[1,-28,[12],13]],[5,1306,371],[14.661,-987.246,0,0,0,0,1,1,1,1]],[0,"button2",1,[[5,"default","animation5",0,"animation5",-29,[14],15]],[5,532,608],[28.883,-358.972,0,0,0,0,1,1,1,1]],[4,"黑布",1,[[3,0,-30,[16],17]],[4,4278190080],[5,1468,2783],[0,-0.15638321919599724,-0.20181221173501607],[495,-1955,0,0,0,0,1,1,1,1]],[4,"黑布 copy",1,[[3,0,-31,[18],19]],[4,4278190080],[5,1468,2783],[0,-0.15638321919599724,-0.20181221173501607],[-2416.102,-1955,0,0,0,0,1,1,1,1]],[0,"上方框",1,[[1,-32,[20],21]],[5,1440,190],[0,1184.704,0,0,0,0,1,1,1,1]]],0,[0,-1,9,0,-2,10,0,-3,3,0,-4,4,0,-5,5,0,-6,6,0,-7,11,0,-8,12,0,-9,13,0,-10,14,0,-11,15,0,0,2,0,0,2,0,0,2,0,0,2,0,-1,8,0,0,3,0,0,3,0,0,4,0,0,4,0,0,5,0,0,5,0,0,6,0,0,6,0,0,8,0,0,9,0,0,10,0,0,11,0,0,12,0,0,13,0,0,14,0,0,15,0,5,7,1,3,2,2,3,7,32],[0,0,0,0,0,0,0,0,0,0,0,0,0,0,0,0,0,0,0,0,0,0],[-1,1,-1,1,-1,1,-1,1,-1,1,-1,4,-1,1,-1,4,-1,1,-1,1,-1,1],[0,12,0,13,0,14,0,1,0,1,2,15,0,16,2,17,0,3,0,3,0,18]]]]